{
  "quotes": [
    {
      "text": "直线调不成，只有搞曲线调动。",
      "source": "《高山下的花环》"
    },
    {
      "text": "知识青年下放的时候，你们怕下乡，都涌到部队里头来。现在感到吃苦啦，又削尖了脑袋，要回大城市。",
      "source": "《高山下的花环》"
    },
    {
      "text": "中国，是我的，可也是你的！",
      "source": "《高山下的花环》"
    },
    {
      "text": "二百个亿养个狼崽子。",
      "source": "《高山下的花环》"
    },
    {
      "text": "副连长，副连长，战前赏了我一个送死的官。",
      "source": "《高山下的花环》"
    },
    {
      "text": "诶，烈士陵园见。",
      "source": "《高山下的花环》"
    },
    {
      "text": "永远不要在人前调侃你的理想，你为它付出的是生命。",
      "source": "《我的团长我的团》"
    },
    {
      "text": "你有逆流而上的勇气，也有漏船载酒的运气。做人做到如此晦气。何不赚个爽快？",
      "source": "《我的团长我的团》"
    },
    {
      "text": "我恨这样，但从小就这样——我夸我强，便有人找来比我强的，我怨我惨，便有人数落比我惨的。我活我的，没人在比较。我们像死啦死啦一样活着，用一把叫自己的尺子量这个世界。",
      "source": "《我的团长我的团》"
    },
    {
      "text": "我们只能带一种闪了腰似的表情，呆呆地看着。聪明人做出蠢事来能把傻子气死。",
      "source": "《我的团长我的团》"
    },
    {
      "text": "打敌人，我能勇敢。可是，敢于提意见，向我们内部那些歪门邪道开炮，你呀，要比我勇敢得多！",
      "source": "《高山下的花环》"
    },
    {
      "text": "时间就是吞噬自己尾巴的一条蛇，我们身在其中，永不知何所谓始，何所谓终。我们最终只能越来越像我们自己。",
      "source": "《我的团长我的团》"
    },
    {
      "text": "打了四年仗，我开始认一个奇怪的理，战场是仁慈的，非生即死，人世间则残酷，它为你准备的东西叫作没数。",
      "source": "《我的团长我的团》"
    },
    {
      "text": "从来没有一只耳朵能被嘴巴真正的说服！",
      "source": "《我的团长我的团》"
    },
    {
      "text": "我，孟烦了，野心勃勃，诸战皆北，一事无成，孤星入命，孑然一身。曾于这战乱之秋誊抄了十几份遗书发给所有亲友，从此就冒充活死人。我回头看着他们，现在就我一个人了，我像阿译一样看着他们的背影发呆。",
      "source": "《我的团长我的团》"
    },
    {
      "text": "中华要灭亡，湖南人先死绝。",
      "source": "《我的团长我的团》"
    },
    {
      "text": "别人死了我可以填上去，我死了别人也可以填上来。",
      "source": "《我的团长我的团》"
    },
    {
      "text": "我只是希望事情是它该有的那个样子",
      "source": "《我的团长我的团》"
    },
    {
      "text": "一尘不染的事情是没有的，我们都在吸进灰尘，可不妨碍我们做的好一点啊",
      "source": "《我的团长我的团》"
    },
    {
      "text": "我们其实就想要一个答案，可答案不该是死",
      "source": "《我的团长我的团》"
    },
    {
      "text": "我的师长，他不是战争狂，他只是焦虑太过了，焦虑太过了。总好过那些没心没肺的醉生梦死吧？一尘不染的事情是没有的，我们都在吸进灰尘，可不妨碍我们做的好一点啊。我们其实就想要一个答案，可答案不该是死",
      "source": "《我的团长我的团》"
    },
    {
      "text": "The truth is out there!",
      "source": "The X-Files"
    },
    {
      "text": "I'll be back.",
      "source": "The Terminator"
    },
    {
      "text": "May the Force be with you.",
      "source": "Star Wars"
    },
    {
      "text": "There's no place like home.",
      "source": "The Wizard of Oz"
    },
    {
      "text": "I am your father.",
      "source": "Star Wars: Episode V - The Empire Strikes Back"
    },
    {
      "text": "Carpe diem. Seize the day, boys. Make your lives extraordinary.",
      "source": "Dead Poets Society"
    },
    {
      "text": "真相只有一个！",
      "source": "名探偵コナン"
    },
    {
      "text": "人は自分の歩みを止めない限り、どこへでも行けるんだよ。",
      "source": "となりのトトロ"
    },
    {
      "text": "人は夢を追い続けるんだ。",
      "source": "新世紀エヴァンゲリオン"
    },
    {
      "text": "僕たちの戦場はここじゃない。僕たちの明日はここじゃない。真実の戦場はあそこだ。そして未来はあそこにしか存在しない。",
      "source": "機動戦士ガンダム"
    }
  ]
}